{
  "project_info": {
    "project_number": "803358715768",
    "project_id": "practica11-25566",
    "storage_bucket": "practica11-25566.appspot.com"
  },
  "client": [
    {
      "client_info": {
        "mobilesdk_app_id": "1:803358715768:android:e6c28d0f2b20580dd2a28d",
        "android_client_info": {
          "package_name": "cl.inacap.app_firebase"
        }
      },
      "oauth_client": [],
      "api_key": [
        {
          "current_key": "AIzaSyDgYZ5Fcj4jBwEXZowRF93XPh64zkQBcDM"
        }
      ],
      "services": {
        "appinvite_service": {
          "other_platform_oauth_client": []
        }
      }
    }
  ],
  "configuration_version": "1"
}